{"web":{"client_id":"8269603118-b1gfroc06siiiqhgoejr8kf6l2k71lvo.apps.googleusercontent.com","project_id":"motohut-security","auth_uri":"https://accounts.google.com/o/oauth2/auth","token_uri":"https://oauth2.googleapis.com/token","auth_provider_x509_cert_url":"https://www.googleapis.com/oauth2/v1/certs","client_secret":"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","redirect_uris":["https://motohut-security.firebaseapp.com/__/auth/handler"],"javascript_origins":["http://localhost","http://localhost:5000","https://motohut-security.firebaseapp.com"]}}